oarepo_whitenoise/__init__.py
oarepo_whitenoise/version.py
oarepo_whitenoise/wsgi.py
tests/__init__.py
tests/test_empty.py
oarepo_whitenoise-2.0.4.dist-info/AUTHORS.rst
oarepo_whitenoise-2.0.4.dist-info/LICENSE
oarepo_whitenoise-2.0.4.dist-info/METADATA
oarepo_whitenoise-2.0.4.dist-info/WHEEL
oarepo_whitenoise-2.0.4.dist-info/top_level.txt
oarepo_whitenoise-2.0.4.dist-info/RECORD
